event_herald/__init__.py
event_herald/cli.py
event_herald/event_herald.py
event_herald-0.1.0.dist-info/AUTHORS.rst
event_herald-0.1.0.dist-info/LICENSE
event_herald-0.1.0.dist-info/METADATA
event_herald-0.1.0.dist-info/WHEEL
event_herald-0.1.0.dist-info/entry_points.txt
event_herald-0.1.0.dist-info/top_level.txt
event_herald-0.1.0.dist-info/RECORD
