Metadata-Version: 2.1
Name: event-herald
Version: 0.1.0
Summary: Framework for event drive programming in python.
Home-page: https://github.com/berecik/event_herald
Author: Adam Beret Manczuk
Author-email: beret@hipisi.org.pl
License: MIT license
Keywords: event_herald
Platform: UNKNOWN
Classifier: Development Status :: 2 - Pre-Alpha
Classifier: Intended Audience :: Developers
Classifier: License :: OSI Approved :: MIT License
Classifier: Natural Language :: English
Classifier: Programming Language :: Python :: 3
Classifier: Programming Language :: Python :: 3.6
Classifier: Programming Language :: Python :: 3.7
Classifier: Programming Language :: Python :: 3.8
Requires-Python: >=3.6
License-File: LICENSE
License-File: AUTHORS.rst
Requires-Dist: Click (>=7.0)
